{"type":"FeatureCollection","crs":{"type":"name","properties":{"name":"EPSG:4326"}},"features":[{"type":"Feature","id":1,"geometry":{"type":"Point","coordinates":[24.026008000369,37.7246549996286,0]},"properties":{"OBJECTID":1,"Join_Count":1,"TARGET_FID":5765,"CREATED":"2011-09-09T21:25:37Z","CREATORS":"J.S. Traill","DESCRIPTIO":"An Athenian lead or silver mine","FEATURETYP":"mine","GEOCONTEXT":"at Laureion (36)","ID":"963101166","LOCATIONPR":"precise","MODIFIED":"2012-10-23T15:45:50Z","PATH":"/places/963101166","REPRLAT":37.724655,"REPRLATLON":"37.724655,24.026008","REPRLONG":24.026008,"TIMEPERIOD":"CHR","TIMEPER_01":"classical,hellenistic-republican,roman","TIMEPER_02":"-550.0,300.0","TITLE":"Mine of Laureion","UID":"62ff12db561995ccbd03846d51d3c43b","AWMC_MOD":0,"MAXDATE":300,"MINDATE":-550,"AWMC_ID":154893,"BBOX":" ","EXTENT":" ","TAGS":"dare:major=0, dare:ancient=2, dare:feature=other","TYPE":"mine","AUTHORS":"Traill, J., DARMC, T. Elliott, R. Talbert, S. Gillies","HASCONNECT":" ","CONNECTSWI":" ","Persia_satrapy":"False","Name":"Greece","Alexander":"True","Comments":null,"Kierpert":null,"KierpertComment":null,"KierpertSpelling":null}}]}